{
  "ppa": {
    "ceiling": 0.814098,
    "adversarial_inceptionv3": 0.801688,
    "aimv2": 0.829153,
    "alexnet": 0.743121,
    "alexnet_random": -0.209516,
    "beit": 0.830974,
    "bit": 0.805185,
    "blip2": 0.84268,
    "briaai": 0.813623,
    "clip_rn101": 0.843962,
    "clip_rn101_random": 0.09434,
    "clip_rn50": 0.834624,
    "clip_rn50_random": 0.21048,
    "clip_vit_b32": 0.821407,
    "clip_vit_b32_random": 0.108941,
    "convnext": 0.832341,
    "cornet_rt": 0.803438,
    "cornet_s": 0.81378,
    "cornet_z": 0.686034,
    "cross_vit": 0.799345,
    "densenet121": 0.827986,
    "densenet161": 0.837166,
    "densenet161_random": 0.249279,
    "densenet169": 0.80306,
    "densenet201": 0.817113,
    "dinov2": 0.830336,
    "dinov2_random": 0.132114,
    "dinov2_large": 0.822925,
    "dreamsim_vitb16": 0.764489,
    "dreamsim_vitb32": 0.767711,
    "efficient_net": 0.821446,
    "ese_vovnet": 0.816454,
    "eva2": 0.828376,
    "fbnet": 0.841358,
    "ghost_net": 0.822181,
    "google_vit": 0.784767,
    "google_vit_random": -0.134297,
    "hrnet": 0.805898,
    "inception_rn_v2": 0.801658,
    "inceptionv3": 0.828124,
    "inceptionv4": 0.803089,
    "kosmos2": 0.83717,
    "mixnet": 0.792211,
    "mnasnet": 0.825889,
    "mobilenetv2": 0.734738,
    "nomic": 0.839278,
    "nomic_random": 0.117194,
    "resnet101": 0.824989,
    "resnet101_random": 0.111213,
    "resnet101_imagenet1kv1": 0.827952,
    "resnet50_places365": 0.825789,
    "resnet50": 0.821334,
    "resnet18": 0.821911,
    "resnet18_random": 0.021364,
    "resnet50_random": 0.08135,
    "resnet50_vggface2": 0.400495,
    "robust_rn18_blur_weak": 0.770288,
    "robust_rn18_blur_strong": 0.771216,
    "robust_rn50_blur_weak": 0.798757,
    "robust_rn50_blur_strong": 0.798214,
    "robust_vgg16_blur_weak": 0.752094,
    "robust_vgg16_blur_strong": 0.755972,
    "robust_vgg19_blur_weak": 0.744021,
    "robust_vgg19_blur_strong": 0.766237,
    "robust_densenet161_epsilon_3": 0.226146,
    "robust_mnasnet_epsilon_3": 0.825566,
    "robust_mobilenetv2_epsilon_3": 0.734738,
    "robust_rn18_epsilon_003": 0.828514,
    "robust_rn18_epsilon_01": 0.816534,
    "robust_rn18_epsilon_025": 0.829781,
    "robust_rn18_epsilon_3": 0.802407,
    "robust_rn18_epsilon_5": 0.796047,
    "robust_rn50_epsilon_003": 0.823239,
    "robust_rn50_epsilon_01": 0.812569,
    "robust_rn50_epsilon_025": 0.820836,
    "robust_rn50_epsilon_3": 0.803679,
    "robust_rn50_epsilon_5": 0.80549,
    "robust_vgg16_bn_epsilon_3": 0.766799,
    "robust_wideresnet50_epsilon_003": 0.831792,
    "robust_wideresnet50_epsilon_01": 0.811042,
    "robust_wideresnet50_epsilon_025": 0.765907,
    "robust_wideresnet50_epsilon_3": 0.804843,
    "robust_wideresnet50_epsilon_5": 0.796441,
    "siglip": 0.834539,
    "siglip2": 0.836928,
    "taskonomy_denoising": 0.312927,
    "taskonomy_autoencoding": 0.328659,
    "taskonomy_curvature": 0.660687,
    "taskonomy_depth_euclidean": 0.662483,
    "taskonomy_depth_zbuffer": 0.677151,
    "taskonomy_class_object": 0.689082,
    "taskonomy_class_scene": 0.675734,
    "taskonomy_edge_occlusion": 0.693077,
    "taskonomy_edge_texture": 0.267215,
    "taskonomy_inpainting": 0.45049,
    "taskonomy_keypoints2d": 0.256962,
    "taskonomy_keypoints3d": 0.701723,
    "taskonomy_normal": 0.684325,
    "taskonomy_reshading": 0.686239,
    "taskonomy_segment_semantic": 0.656499,
    "taskonomy_segment_unsup25d": 0.605079,
    "taskonomy_segment_unsup2d": 0.427544,
    "tdann_simclr": 0.762643,
    "tdann_simclr_alpha_2": 0.795208,
    "tdann_simclr_alpha_5": 0.776181,
    "tdann_simclr_alpha_10": 0.694609,
    "tdann_simclr_alpha_100": 0.630155,
    "toponets_rn18": 0.795082,
    "toponets_rn18_tau_0.5": 0.770146,
    "toponets_rn18_tau_1": 0.821404,
    "toponets_rn18_tau_5": 0.817008,
    "toponets_rn18_tau_20": 0.801199,
    "toponets_rn18_tau_50": 0.791399,
    "toponets_rn50": 0.764817,
    "toponets_vit": 0.801892,
    "vgg16_imagenet1kv1": 0.770719,
    "vgg16_imagenet1kv1_random": 0.05675,
    "vgg19_imagenet1kv1": 0.762071,
    "vgg19_imagenet1kv1_random": 0.218065,
    "vone_alexnet": 0.348689,
    "vone_cornet_s": 0.346762,
    "vone_rn50": 0.404156,
    "webssl_mae300m": 0.809965,
    "webssl_dino300m": 0.813401,
    "wideresnet101": 0.793566,
    "wideresnet50": 0.832344,
    "xception": 0.814768
  },
  "ffa": {
    "ceiling": 0.820121,
    "adversarial_inceptionv3": 0.767688,
    "aimv2": 0.859885,
    "alexnet": 0.757016,
    "alexnet_random": 0.001597,
    "beit": 0.802323,
    "bit": 0.782128,
    "blip2": 0.817223,
    "briaai": 0.804698,
    "clip_rn101": 0.841126,
    "clip_rn101_random": 0.257022,
    "clip_rn50": 0.849183,
    "clip_rn50_random": 0.053908,
    "clip_vit_b32": 0.783026,
    "clip_vit_b32_random": 0.215339,
    "convnext": 0.788645,
    "cornet_rt": 0.840531,
    "cornet_s": 0.816585,
    "cornet_z": 0.757527,
    "cross_vit": 0.798553,
    "densenet121": 0.804473,
    "densenet161": 0.829847,
    "densenet161_random": 0.412733,
    "densenet169": 0.812224,
    "densenet201": 0.814165,
    "dinov2": 0.82783,
    "dinov2_random": 0.194622,
    "dinov2_large": 0.818592,
    "dreamsim_vitb16": 0.804063,
    "dreamsim_vitb32": 0.795347,
    "efficient_net": 0.828974,
    "ese_vovnet": 0.782667,
    "eva2": 0.841309,
    "fbnet": 0.80477,
    "ghost_net": 0.803781,
    "google_vit": 0.785452,
    "google_vit_random": 0.105903,
    "hrnet": 0.810634,
    "inception_rn_v2": 0.821881,
    "inceptionv3": 0.787038,
    "inceptionv4": 0.788673,
    "kosmos2": 0.83829,
    "mixnet": 0.754013,
    "mnasnet": 0.760239,
    "mobilenetv2": 0.816868,
    "nomic": 0.848095,
    "nomic_random": 0.284683,
    "resnet101": 0.852353,
    "resnet101_random": 0.143075,
    "resnet101_imagenet1kv1": 0.814312,
    "resnet50_places365": 0.783741,
    "resnet50": 0.827756,
    "resnet18": 0.796508,
    "resnet18_random": 0.309672,
    "resnet50_random": 0.037346,
    "resnet50_vggface2": 0.429222,
    "robust_rn18_blur_weak": 0.799621,
    "robust_rn18_blur_strong": 0.796751,
    "robust_rn50_blur_weak": 0.816655,
    "robust_rn50_blur_strong": 0.805572,
    "robust_vgg16_blur_weak": 0.762092,
    "robust_vgg16_blur_strong": 0.798014,
    "robust_vgg19_blur_weak": 0.742003,
    "robust_vgg19_blur_strong": 0.781682,
    "robust_densenet161_epsilon_3": 0.409879,
    "robust_mnasnet_epsilon_3": 0.760788,
    "robust_mobilenetv2_epsilon_3": 0.816868,
    "robust_rn18_epsilon_003": 0.800367,
    "robust_rn18_epsilon_01": 0.811395,
    "robust_rn18_epsilon_025": 0.807694,
    "robust_rn18_epsilon_3": 0.801369,
    "robust_rn18_epsilon_5": 0.767851,
    "robust_rn50_epsilon_003": 0.818983,
    "robust_rn50_epsilon_01": 0.821144,
    "robust_rn50_epsilon_025": 0.808234,
    "robust_rn50_epsilon_3": 0.820587,
    "robust_rn50_epsilon_5": 0.788146,
    "robust_vgg16_bn_epsilon_3": 0.827842,
    "robust_wideresnet50_epsilon_003": 0.785647,
    "robust_wideresnet50_epsilon_01": 0.807377,
    "robust_wideresnet50_epsilon_025": 0.801444,
    "robust_wideresnet50_epsilon_3": 0.820467,
    "robust_wideresnet50_epsilon_5": 0.793024,
    "siglip": 0.81927,
    "siglip2": 0.853067,
    "taskonomy_denoising": 0.497301,
    "taskonomy_autoencoding": 0.375359,
    "taskonomy_curvature": 0.593044,
    "taskonomy_depth_euclidean": 0.530098,
    "taskonomy_depth_zbuffer": 0.583199,
    "taskonomy_class_object": 0.57866,
    "taskonomy_class_scene": 0.556923,
    "taskonomy_edge_occlusion": 0.656333,
    "taskonomy_edge_texture": 0.385251,
    "taskonomy_inpainting": 0.534805,
    "taskonomy_keypoints2d": 0.2352,
    "taskonomy_keypoints3d": 0.578073,
    "taskonomy_normal": 0.648818,
    "taskonomy_reshading": 0.570758,
    "taskonomy_segment_semantic": 0.593523,
    "taskonomy_segment_unsup25d": 0.581555,
    "taskonomy_segment_unsup2d": 0.370146,
    "tdann_simclr": 0.803327,
    "tdann_simclr_alpha_2": 0.805754,
    "tdann_simclr_alpha_5": 0.806213,
    "tdann_simclr_alpha_10": 0.780401,
    "tdann_simclr_alpha_100": 0.550075,
    "toponets_rn18": 0.783066,
    "toponets_rn18_tau_0.5": 0.814825,
    "toponets_rn18_tau_1": 0.820034,
    "toponets_rn18_tau_5": 0.788685,
    "toponets_rn18_tau_20": 0.783025,
    "toponets_rn18_tau_50": 0.768775,
    "toponets_rn50": 0.824386,
    "toponets_vit": 0.784952,
    "vgg16_imagenet1kv1": 0.779714,
    "vgg16_imagenet1kv1_random": 0.09522,
    "vgg19_imagenet1kv1": 0.809442,
    "vgg19_imagenet1kv1_random": 0.087902,
    "vone_alexnet": 0.370863,
    "vone_cornet_s": 0.372174,
    "vone_rn50": 0.393284,
    "webssl_mae300m": 0.798638,
    "webssl_dino300m": 0.776941,
    "wideresnet101": 0.801084,
    "wideresnet50": 0.82638,
    "xception": 0.781624
  },
  "eba": {
    "ceiling": 0.845164,
    "adversarial_inceptionv3": 0.736968,
    "aimv2": 0.795749,
    "alexnet": 0.69933,
    "alexnet_random": 0.125684,
    "beit": 0.807528,
    "bit": 0.771825,
    "blip2": 0.774574,
    "briaai": 0.704946,
    "clip_rn101": 0.741791,
    "clip_rn101_random": 0.238483,
    "clip_rn50": 0.758709,
    "clip_rn50_random": 0.234609,
    "clip_vit_b32": 0.77165,
    "clip_vit_b32_random": 0.132159,
    "convnext": 0.787214,
    "cornet_rt": 0.71346,
    "cornet_s": 0.786025,
    "cornet_z": 0.630252,
    "cross_vit": 0.656318,
    "densenet121": 0.768181,
    "densenet161": 0.803884,
    "densenet161_random": 0.265141,
    "densenet169": 0.784541,
    "densenet201": 0.778927,
    "dinov2": 0.816393,
    "dinov2_random": 0.208898,
    "dinov2_large": 0.781498,
    "dreamsim_vitb16": 0.673039,
    "dreamsim_vitb32": 0.781357,
    "efficient_net": 0.778389,
    "ese_vovnet": 0.785707,
    "eva2": 0.694559,
    "fbnet": 0.817938,
    "ghost_net": 0.726777,
    "google_vit": 0.717867,
    "google_vit_random": -0.280963,
    "hrnet": 0.790988,
    "inception_rn_v2": 0.729546,
    "inceptionv3": 0.767382,
    "inceptionv4": 0.763409,
    "kosmos2": 0.739456,
    "mixnet": 0.768135,
    "mnasnet": 0.817992,
    "mobilenetv2": 0.708256,
    "nomic": 0.800871,
    "nomic_random": 0.205769,
    "resnet101": 0.759932,
    "resnet101_random": 0.075831,
    "resnet101_imagenet1kv1": 0.777975,
    "resnet50_places365": 0.76133,
    "resnet50": 0.816006,
    "resnet18": 0.788681,
    "resnet18_random": 0.063017,
    "resnet50_random": 0.09992,
    "resnet50_vggface2": 0.384363,
    "robust_rn18_blur_weak": 0.638563,
    "robust_rn18_blur_strong": 0.626328,
    "robust_rn50_blur_weak": 0.65717,
    "robust_rn50_blur_strong": 0.629343,
    "robust_vgg16_blur_weak": 0.655047,
    "robust_vgg16_blur_strong": 0.532953,
    "robust_vgg19_blur_weak": 0.646173,
    "robust_vgg19_blur_strong": 0.590107,
    "robust_densenet161_epsilon_3": 0.305241,
    "robust_mnasnet_epsilon_3": 0.816738,
    "robust_mobilenetv2_epsilon_3": 0.708256,
    "robust_rn18_epsilon_003": 0.78214,
    "robust_rn18_epsilon_01": 0.746384,
    "robust_rn18_epsilon_025": 0.763492,
    "robust_rn18_epsilon_3": 0.705919,
    "robust_rn18_epsilon_5": 0.650702,
    "robust_rn50_epsilon_003": 0.759135,
    "robust_rn50_epsilon_01": 0.80095,
    "robust_rn50_epsilon_025": 0.797876,
    "robust_rn50_epsilon_3": 0.660723,
    "robust_rn50_epsilon_5": 0.68119,
    "robust_vgg16_bn_epsilon_3": 0.726486,
    "robust_wideresnet50_epsilon_003": 0.815793,
    "robust_wideresnet50_epsilon_01": 0.807699,
    "robust_wideresnet50_epsilon_025": 0.812493,
    "robust_wideresnet50_epsilon_3": 0.668884,
    "robust_wideresnet50_epsilon_5": 0.711877,
    "siglip": 0.79193,
    "siglip2": 0.79696,
    "taskonomy_denoising": 0.283218,
    "taskonomy_autoencoding": 0.348029,
    "taskonomy_curvature": 0.279078,
    "taskonomy_depth_euclidean": 0.367331,
    "taskonomy_depth_zbuffer": 0.392505,
    "taskonomy_class_object": 0.518546,
    "taskonomy_class_scene": 0.407032,
    "taskonomy_edge_occlusion": 0.468453,
    "taskonomy_edge_texture": 0.362304,
    "taskonomy_inpainting": 0.345227,
    "taskonomy_keypoints2d": 0.346003,
    "taskonomy_keypoints3d": 0.437191,
    "taskonomy_normal": 0.450359,
    "taskonomy_reshading": 0.414817,
    "taskonomy_segment_semantic": 0.342813,
    "taskonomy_segment_unsup25d": 0.460414,
    "taskonomy_segment_unsup2d": 0.345921,
    "tdann_simclr": 0.742107,
    "tdann_simclr_alpha_2": 0.685546,
    "tdann_simclr_alpha_5": 0.718451,
    "tdann_simclr_alpha_10": 0.601075,
    "tdann_simclr_alpha_100": 0.255824,
    "toponets_rn18": 0.743266,
    "toponets_rn18_tau_0.5": 0.745272,
    "toponets_rn18_tau_1": 0.741033,
    "toponets_rn18_tau_5": 0.719247,
    "toponets_rn18_tau_20": 0.718856,
    "toponets_rn18_tau_50": 0.719211,
    "toponets_rn50": 0.739856,
    "toponets_vit": 0.650445,
    "vgg16_imagenet1kv1": 0.718872,
    "vgg16_imagenet1kv1_random": 0.116136,
    "vgg19_imagenet1kv1": 0.719099,
    "vgg19_imagenet1kv1_random": 0.261486,
    "vone_alexnet": 0.247783,
    "vone_cornet_s": 0.241368,
    "vone_rn50": 0.273304,
    "webssl_mae300m": 0.73444,
    "webssl_dino300m": 0.777954,
    "wideresnet101": 0.76885,
    "wideresnet50": 0.797852,
    "xception": 0.752203
  },
  "Overall": {
    "ceiling": 0.826461,
    "adversarial_inceptionv3": 0.7687813333333334,
    "aimv2": 0.8282623333333333,
    "alexnet": 0.7331556666666668,
    "alexnet_random": -0.027411666666666678,
    "beit": 0.8136083333333334,
    "bit": 0.7863793333333332,
    "blip2": 0.8114923333333333,
    "briaai": 0.7744223333333333,
    "clip_rn101": 0.8089596666666666,
    "clip_rn101_random": 0.19661499999999998,
    "clip_rn50": 0.814172,
    "clip_rn50_random": 0.16633233333333333,
    "clip_vit_b32": 0.7920276666666667,
    "clip_vit_b32_random": 0.15214633333333336,
    "convnext": 0.8027333333333333,
    "cornet_rt": 0.7858096666666666,
    "cornet_s": 0.8054633333333333,
    "cornet_z": 0.691271,
    "cross_vit": 0.7514053333333331,
    "densenet121": 0.8002133333333333,
    "densenet161": 0.8236323333333333,
    "densenet161_random": 0.309051,
    "densenet169": 0.7999416666666667,
    "densenet201": 0.8034016666666667,
    "dinov2": 0.8248530000000001,
    "dinov2_random": 0.17854466666666668,
    "dinov2_large": 0.8076716666666667,
    "dreamsim_vitb16": 0.747197,
    "dreamsim_vitb32": 0.7814716666666667,
    "efficient_net": 0.8096030000000001,
    "ese_vovnet": 0.7949426666666667,
    "eva2": 0.7880813333333333,
    "fbnet": 0.8213553333333333,
    "ghost_net": 0.7842463333333333,
    "google_vit": 0.7626953333333333,
    "google_vit_random": -0.103119,
    "hrnet": 0.8025066666666666,
    "inception_rn_v2": 0.7843616666666667,
    "inceptionv3": 0.7941813333333334,
    "inceptionv4": 0.7850570000000001,
    "kosmos2": 0.8049719999999999,
    "mixnet": 0.771453,
    "mnasnet": 0.8013733333333333,
    "mobilenetv2": 0.7532873333333333,
    "nomic": 0.8294146666666666,
    "nomic_random": 0.20254866666666668,
    "resnet101": 0.8124246666666667,
    "resnet101_random": 0.11003966666666666,
    "resnet101_imagenet1kv1": 0.8067463333333333,
    "resnet50_places365": 0.7902866666666667,
    "resnet50": 0.8216986666666667,
    "resnet18": 0.8023666666666666,
    "resnet18_random": 0.131351,
    "resnet50_random": 0.07287199999999999,
    "resnet50_vggface2": 0.40469333333333335,
    "robust_rn18_blur_weak": 0.7361573333333333,
    "robust_rn18_blur_strong": 0.7314316666666666,
    "robust_rn50_blur_weak": 0.7575273333333333,
    "robust_rn50_blur_strong": 0.7443763333333333,
    "robust_vgg16_blur_weak": 0.7230776666666667,
    "robust_vgg16_blur_strong": 0.6956463333333334,
    "robust_vgg19_blur_weak": 0.7107323333333334,
    "robust_vgg19_blur_strong": 0.7126753333333333,
    "robust_densenet161_epsilon_3": 0.31375533333333333,
    "robust_mnasnet_epsilon_3": 0.8010306666666667,
    "robust_mobilenetv2_epsilon_3": 0.7532873333333333,
    "robust_rn18_epsilon_003": 0.8036736666666666,
    "robust_rn18_epsilon_01": 0.7914376666666666,
    "robust_rn18_epsilon_025": 0.8003223333333334,
    "robust_rn18_epsilon_3": 0.7698983333333332,
    "robust_rn18_epsilon_5": 0.7382,
    "robust_rn50_epsilon_003": 0.8004523333333333,
    "robust_rn50_epsilon_01": 0.8115543333333334,
    "robust_rn50_epsilon_025": 0.808982,
    "robust_rn50_epsilon_3": 0.761663,
    "robust_rn50_epsilon_5": 0.7582753333333333,
    "robust_vgg16_bn_epsilon_3": 0.7737089999999999,
    "robust_wideresnet50_epsilon_003": 0.8110773333333334,
    "robust_wideresnet50_epsilon_01": 0.8087059999999999,
    "robust_wideresnet50_epsilon_025": 0.7932813333333333,
    "robust_wideresnet50_epsilon_3": 0.7647313333333333,
    "robust_wideresnet50_epsilon_5": 0.767114,
    "siglip": 0.8152463333333334,
    "siglip2": 0.828985,
    "taskonomy_denoising": 0.364482,
    "taskonomy_autoencoding": 0.3506823333333333,
    "taskonomy_curvature": 0.5109363333333333,
    "taskonomy_depth_euclidean": 0.5199706666666667,
    "taskonomy_depth_zbuffer": 0.5509516666666666,
    "taskonomy_class_object": 0.5954293333333333,
    "taskonomy_class_scene": 0.546563,
    "taskonomy_edge_occlusion": 0.6059543333333334,
    "taskonomy_edge_texture": 0.33825666666666665,
    "taskonomy_inpainting": 0.4435073333333333,
    "taskonomy_keypoints2d": 0.27938833333333335,
    "taskonomy_keypoints3d": 0.572329,
    "taskonomy_normal": 0.5945006666666667,
    "taskonomy_reshading": 0.5572713333333333,
    "taskonomy_segment_semantic": 0.530945,
    "taskonomy_segment_unsup25d": 0.5490160000000001,
    "taskonomy_segment_unsup2d": 0.38120366666666666,
    "tdann_simclr": 0.769359,
    "tdann_simclr_alpha_2": 0.7621693333333334,
    "tdann_simclr_alpha_5": 0.7669483333333332,
    "tdann_simclr_alpha_10": 0.6920283333333334,
    "tdann_simclr_alpha_100": 0.47868466666666665,
    "toponets_rn18": 0.7738046666666666,
    "toponets_rn18_tau_0.5": 0.7767476666666666,
    "toponets_rn18_tau_1": 0.7941569999999999,
    "toponets_rn18_tau_5": 0.7749799999999999,
    "toponets_rn18_tau_20": 0.7676933333333333,
    "toponets_rn18_tau_50": 0.759795,
    "toponets_rn50": 0.776353,
    "toponets_vit": 0.7457630000000001,
    "vgg16_imagenet1kv1": 0.7564350000000001,
    "vgg16_imagenet1kv1_random": 0.08936866666666667,
    "vgg19_imagenet1kv1": 0.7635373333333333,
    "vgg19_imagenet1kv1_random": 0.18915099999999999,
    "vone_alexnet": 0.322445,
    "vone_cornet_s": 0.32010133333333335,
    "vone_rn50": 0.35691466666666666,
    "webssl_mae300m": 0.7810143333333333,
    "webssl_dino300m": 0.789432,
    "wideresnet101": 0.7878333333333334,
    "wideresnet50": 0.8188586666666667,
    "xception": 0.782865
  }
}